sphinxcontrib/swagger2sphinx.py
sphinxcontrib_swagger2sphinx-0.1.4.dist-info/DESCRIPTION.rst
sphinxcontrib_swagger2sphinx-0.1.4.dist-info/METADATA
sphinxcontrib_swagger2sphinx-0.1.4.dist-info/RECORD
sphinxcontrib_swagger2sphinx-0.1.4.dist-info/WHEEL
sphinxcontrib_swagger2sphinx-0.1.4.dist-info/metadata.json
sphinxcontrib_swagger2sphinx-0.1.4.dist-info/top_level.txt
