Metadata-Version: 2.0
Name: sphinxcontrib-swagger2sphinx
Version: 0.1.4
Summary: Converter from Swagger to Sphinx HTTP domain.
Home-page: https://bitbucket.org/moigagoo/sphinxcontrib-swagger2sphinx
Author: Konstantin Molchanov
Author-email: moigagoo@live.com
License: MIT
Download-URL: https://pypi.org/project/sphinxcontrib-swagger2sphinx
Platform: any
Classifier: Development Status :: 4 - Beta
Classifier: Environment :: Console
Classifier: Environment :: Web Environment
Classifier: Intended Audience :: Developers
Classifier: License :: OSI Approved :: MIT License
Classifier: Operating System :: OS Independent
Classifier: Programming Language :: Python
Classifier: Topic :: Documentation
Classifier: Topic :: Utilities
Requires-Dist: Sphinx (>=1.0)
Requires-Dist: requests
